dillo/__init__.py
dillo/auth.py
dillo/lib.py
dillo/magic.py
dillo/routes.py
dillo/service.py
dillo/validation.py
dillo/version.py
pydillo-0.2.2.dist-info/METADATA
pydillo-0.2.2.dist-info/WHEEL
pydillo-0.2.2.dist-info/top_level.txt
pydillo-0.2.2.dist-info/RECORD
