Metadata-Version: 2.1
Name: pydillo
Version: 0.2.2
Summary: Common Dillo Development Module
Author: Erick Salas
Author-email: it@dillostores.com
Classifier: Programming Language :: Python :: 3
Classifier: License :: OSI Approved :: MIT License
Classifier: Operating System :: OS Independent
Requires-Python: >=3.6
